{"get":"fixtures","parameters":{"id":"1034710"},"errors":[],"results":1,"paging":{"current":1,"total":1},"response":[{"fixture":{"id":1034710,"referee":"A. \u010culina","timezone":"UTC","date":"2023-09-03T16:30:00+00:00","timestamp":1693758600,"periods":{"first":1693758600,"second":1693762200},"venue":{"id":423,"name":"Stadion HNK Rijeka","city":"Rijeka"},"status":{"long":"Match Finished","short":"FT","elapsed":90}},"league":{"id":210,"name":"HNL","country":"Croatia","logo":"https:\/\/media.api-sports.io\/football\/leagues\/210.png","flag":"https:\/\/media.api-sports.io\/flags\/hr.svg","season":2023,"round":"Regular Season - 7"},"teams":{"home":{"id":561,"name":"HNK Rijeka","logo":"https:\/\/media.api-sports.io\/football\/teams\/561.png","winner":null},"away":{"id":1483,"name":"NK Varazdin","logo":"https:\/\/media.api-sports.io\/football\/teams\/1483.png","winner":null}},"goals":{"home":2,"away":2},"score":{"halftime":{"home":1,"away":0},"fulltime":{"home":2,"away":2},"extratime":{"home":null,"away":null},"penalty":{"home":null,"away":null}},"events":[{"time":{"elapsed":17,"extra":null},"team":{"id":561,"name":"HNK Rijeka","logo":"https:\/\/media.api-sports.io\/football\/teams\/561.png"},"player":{"id":14705,"name":"N. Jankovi\u0107"},"assist":{"id":284869,"name":"T. Fruk"},"type":"Goal","detail":"Normal Goal","comments":null},{"time":{"elapsed":21,"extra":null},"team":{"id":561,"name":"HNK Rijeka","logo":"https:\/\/media.api-sports.io\/football\/teams\/561.png"},"player":{"id":135957,"name":"Veldin Hod\u017ea"},"assist":{"id":null,"name":null},"type":"Card","detail":"Yellow Card","comments":"Foul"},{"time":{"elapsed":46,"extra":null},"team":{"id":1483,"name":"NK Varazdin","logo":"https:\/\/media.api-sports.io\/football\/teams\/1483.png"},"player":{"id":295976,"name":"L. Belcar"},"assist":{"id":90736,"name":"A. Vuku\u0161i\u0107"},"type":"subst","detail":"Substitution 1","comments":null},{"time":{"elapsed":58,"extra":null},"team":{"id":1483,"name":"NK Varazdin","logo":"https:\/\/media.api-sports.io\/football\/teams\/1483.png"},"player":{"id":79944,"name":"L. Jeleni\u0107"},"assist":{"id":14445,"name":"I. Neki\u0107"},"type":"subst","detail":"Substitution 2","comments":null},{"time":{"elapsed":59,"extra":null},"team":{"id":561,"name":"HNK Rijeka","logo":"https:\/\/media.api-sports.io\/football\/teams\/561.png"},"player":{"id":202951,"name":"F. Ivanovi\u0107"},"assist":{"id":30413,"name":"M. Pjaca"},"type":"subst","detail":"Substitution 1","comments":null},{"time":{"elapsed":59,"extra":null},"team":{"id":561,"name":"HNK Rijeka","logo":"https:\/\/media.api-sports.io\/football\/teams\/561.png"},"player":{"id":108453,"name":"L. Selahi"},"assist":{"id":215840,"name":"S. Ilinkovi\u0107"},"type":"subst","detail":"Substitution 2","comments":null},{"time":{"elapsed":69,"extra":null},"team":{"id":561,"name":"HNK Rijeka","logo":"https:\/\/media.api-sports.io\/football\/teams\/561.png"},"player":{"id":70,"name":"Matej Mitrovi\u0107"},"assist":{"id":null,"name":null},"type":"Card","detail":"Yellow Card","comments":"Foul"},{"time":{"elapsed":69,"extra":null},"team":{"id":1483,"name":"NK Varazdin","logo":"https:\/\/media.api-sports.io\/football\/teams\/1483.png"},"player":{"id":14457,"name":"I. Postonjski"},"assist":{"id":null,"name":null},"type":"Goal","detail":"Penalty","comments":null},{"time":{"elapsed":72,"extra":null},"team":{"id":561,"name":"HNK Rijeka","logo":"https:\/\/media.api-sports.io\/football\/teams\/561.png"},"player":{"id":260865,"name":"M. Pa\u0161ali\u0107"},"assist":{"id":13554,"name":"J. Obreg\u00f3n"},"type":"subst","detail":"Substitution 3","comments":null},{"time":{"elapsed":73,"extra":null},"team":{"id":1483,"name":"NK Varazdin","logo":"https:\/\/media.api-sports.io\/football\/teams\/1483.png"},"player":{"id":30904,"name":"F. Brodi\u0107"},"assist":{"id":163483,"name":"D. Mitrovski"},"type":"Goal","detail":"Normal Goal","comments":null},{"time":{"elapsed":77,"extra":null},"team":{"id":561,"name":"HNK Rijeka","logo":"https:\/\/media.api-sports.io\/football\/teams\/561.png"},"player":{"id":14705,"name":"Niko Jankovi\u0107"},"assist":{"id":null,"name":null},"type":"Card","detail":"Yellow Card","comments":"Foul"},{"time":{"elapsed":78,"extra":null},"team":{"id":561,"name":"HNK Rijeka","logo":"https:\/\/media.api-sports.io\/football\/teams\/561.png"},"player":{"id":135957,"name":"V. Hod\u017ea"},"assist":{"id":21033,"name":"E. Banda"},"type":"subst","detail":"Substitution 4","comments":null},{"time":{"elapsed":78,"extra":null},"team":{"id":561,"name":"HNK Rijeka","logo":"https:\/\/media.api-sports.io\/football\/teams\/561.png"},"player":{"id":284869,"name":"T. Fruk"},"assist":{"id":14308,"name":"A. Grgi\u0107"},"type":"subst","detail":"Substitution 5","comments":null},{"time":{"elapsed":80,"extra":null},"team":{"id":1483,"name":"NK Varazdin","logo":"https:\/\/media.api-sports.io\/football\/teams\/1483.png"},"player":{"id":14457,"name":"I. Postonjski"},"assist":{"id":125702,"name":"D. Mistrafovi\u0107"},"type":"subst","detail":"Substitution 3","comments":null},{"time":{"elapsed":80,"extra":null},"team":{"id":1483,"name":"NK Varazdin","logo":"https:\/\/media.api-sports.io\/football\/teams\/1483.png"},"player":{"id":163483,"name":"D. Mitrovski"},"assist":{"id":215929,"name":"L. \u0160kari\u010di\u0107"},"type":"subst","detail":"Substitution 4","comments":null},{"time":{"elapsed":83,"extra":null},"team":{"id":1483,"name":"NK Varazdin","logo":"https:\/\/media.api-sports.io\/football\/teams\/1483.png"},"player":{"id":3605,"name":"Jorgo P\u00ebllumbi"},"assist":{"id":null,"name":null},"type":"Card","detail":"Red Card","comments":"Professional foul last man"},{"time":{"elapsed":85,"extra":null},"team":{"id":561,"name":"HNK Rijeka","logo":"https:\/\/media.api-sports.io\/football\/teams\/561.png"},"player":{"id":13554,"name":"J. Obreg\u00f3n"},"assist":{"id":null,"name":null},"type":"Goal","detail":"Normal Goal","comments":null},{"time":{"elapsed":86,"extra":null},"team":{"id":1483,"name":"NK Varazdin","logo":"https:\/\/media.api-sports.io\/football\/teams\/1483.png"},"player":{"id":30904,"name":"F. Brodi\u0107"},"assist":{"id":328631,"name":"L. Banovec"},"type":"subst","detail":"Substitution 5","comments":null},{"time":{"elapsed":90,"extra":5},"team":{"id":1483,"name":"NK Varazdin","logo":"https:\/\/media.api-sports.io\/football\/teams\/1483.png"},"player":{"id":37361,"name":"Oliver Zelenika"},"assist":{"id":null,"name":null},"type":"Card","detail":"Yellow Card","comments":"Time wasting"}],"lineups":[{"team":{"id":561,"name":"HNK Rijeka","logo":"https:\/\/media.api-sports.io\/football\/teams\/561.png","colors":{"player":{"primary":"ffffff","number":"66ccff","border":"ffffff"},"goalkeeper":{"primary":"e9c205","number":"030303","border":"e9c205"}}},"coach":{"id":20600,"name":"D. Rai\u0107","photo":"https:\/\/media.api-sports.io\/football\/coachs\/20600.png"},"formation":"4-2-3-1","startXI":[{"player":{"id":14553,"name":"N. Labrovi\u0107","number":1,"pos":"G","grid":"1:1"}},{"player":{"id":14266,"name":"I. Smol\u010di\u0107","number":28,"pos":"D","grid":"2:4"}},{"player":{"id":263476,"name":"N. Gale\u0161i\u0107","number":5,"pos":"D","grid":"2:3"}},{"player":{"id":70,"name":"M. Mitrovi\u0107","number":6,"pos":"D","grid":"2:2"}},{"player":{"id":14410,"name":"B. Goda","number":3,"pos":"D","grid":"2:1"}},{"player":{"id":108453,"name":"L. Selahi","number":18,"pos":"M","grid":"3:2"}},{"player":{"id":135957,"name":"V. Hod\u017ea","number":25,"pos":"M","grid":"3:1"}},{"player":{"id":260865,"name":"M. Pa\u0161ali\u0107","number":87,"pos":"M","grid":"4:3"}},{"player":{"id":284869,"name":"T. Fruk","number":21,"pos":"M","grid":"4:2"}},{"player":{"id":14705,"name":"N. Jankovi\u0107","number":4,"pos":"M","grid":"4:1"}},{"player":{"id":202951,"name":"F. Ivanovi\u0107","number":89,"pos":"F","grid":"5:1"}}],"substitutes":[{"player":{"id":30413,"name":"M. Pjaca","number":20,"pos":"M","grid":null}},{"player":{"id":215840,"name":"S. Ilinkovi\u0107","number":27,"pos":"M","grid":null}},{"player":{"id":13554,"name":"J. Obreg\u00f3n","number":9,"pos":"M","grid":null}},{"player":{"id":14308,"name":"A. Grgi\u0107","number":23,"pos":"D","grid":null}},{"player":{"id":21033,"name":"E. Banda","number":22,"pos":"M","grid":null}},{"player":{"id":1307,"name":"E. Dilaver","number":66,"pos":"D","grid":null}},{"player":{"id":14358,"name":"M. \u010cabraja","number":32,"pos":"D","grid":null}},{"player":{"id":14286,"name":"A. Liber","number":8,"pos":"M","grid":null}},{"player":{"id":14285,"name":"I. Lepinjica","number":12,"pos":"M","grid":null}},{"player":{"id":161702,"name":"Danilo Veiga","number":77,"pos":"D","grid":null}},{"player":{"id":108370,"name":"M. Zlomisli\u0107","number":13,"pos":"G","grid":null}},{"player":{"id":14428,"name":"B. Bogojevi\u0107","number":30,"pos":"F","grid":null}}]},{"team":{"id":1483,"name":"NK Varazdin","logo":"https:\/\/media.api-sports.io\/football\/teams\/1483.png","colors":{"player":{"primary":"800000","number":"ffffff","border":"800000"},"goalkeeper":{"primary":"d5862f","number":"222226","border":"d5862f"}}},"coach":{"id":10720,"name":"M. Kova\u010devi\u0107","photo":"https:\/\/media.api-sports.io\/football\/coachs\/10720.png"},"formation":"4-2-3-1","startXI":[{"player":{"id":37361,"name":"O. Zelenika","number":1,"pos":"G","grid":"1:1"}},{"player":{"id":29998,"name":"M. Vuk\u010devi\u0107","number":19,"pos":"D","grid":"2:4"}},{"player":{"id":79944,"name":"L. Jeleni\u0107","number":26,"pos":"D","grid":"2:3"}},{"player":{"id":3605,"name":"J. P\u00ebllumbi","number":4,"pos":"D","grid":"2:2"}},{"player":{"id":33387,"name":"K. Bru\u010di\u0107","number":3,"pos":"D","grid":"2:1"}},{"player":{"id":14457,"name":"I. Postonjski","number":8,"pos":"M","grid":"3:2"}},{"player":{"id":146044,"name":"A. Elezi","number":22,"pos":"M","grid":"3:1"}},{"player":{"id":163483,"name":"D. Mitrovski","number":17,"pos":"M","grid":"4:3"}},{"player":{"id":295976,"name":"L. Belcar","number":10,"pos":"M","grid":"4:2"}},{"player":{"id":14352,"name":"M. \u0160ego","number":11,"pos":"M","grid":"4:1"}},{"player":{"id":30904,"name":"F. Brodi\u0107","number":7,"pos":"F","grid":"5:1"}}],"substitutes":[{"player":{"id":90736,"name":"A. Vuku\u0161i\u0107","number":30,"pos":"F","grid":null}},{"player":{"id":14445,"name":"I. Neki\u0107","number":6,"pos":"D","grid":null}},{"player":{"id":125702,"name":"D. Mistrafovi\u0107","number":20,"pos":"M","grid":null}},{"player":{"id":215929,"name":"L. \u0160kari\u010di\u0107","number":28,"pos":"D","grid":null}},{"player":{"id":328631,"name":"L. Banovec","number":15,"pos":"M","grid":null}},{"player":{"id":337626,"name":"N. Domjani\u0107","number":29,"pos":"F","grid":null}},{"player":{"id":14610,"name":"J. Sili\u0107","number":12,"pos":"G","grid":null}},{"player":{"id":283707,"name":"K. Lusavec","number":14,"pos":"M","grid":null}},{"player":{"id":14400,"name":"D. Dro\u017e\u0111ek","number":9,"pos":"F","grid":null}},{"player":{"id":326627,"name":"N. Vugrinec","number":16,"pos":"F","grid":null}},{"player":{"id":14549,"name":"L. Vuk","number":13,"pos":"M","grid":null}},{"player":{"id":14508,"name":"A. Bor\u0161i\u0107","number":25,"pos":"D","grid":null}}]}],"statistics":[{"team":{"id":561,"name":"HNK Rijeka","logo":"https:\/\/media.api-sports.io\/football\/teams\/561.png"},"statistics":[{"type":"Shots on Goal","value":4},{"type":"Shots off Goal","value":11},{"type":"Total Shots","value":22},{"type":"Blocked Shots","value":7},{"type":"Shots insidebox","value":12},{"type":"Shots outsidebox","value":10},{"type":"Fouls","value":12},{"type":"Corner Kicks","value":12},{"type":"Offsides","value":null},{"type":"Ball Possession","value":"59%"},{"type":"Yellow Cards","value":3},{"type":"Red Cards","value":0},{"type":"Goalkeeper Saves","value":1},{"type":"Total passes","value":455},{"type":"Passes accurate","value":359},{"type":"Passes %","value":"79%"},{"type":"expected_goals","value":"2.60"}]},{"team":{"id":1483,"name":"NK Varazdin","logo":"https:\/\/media.api-sports.io\/football\/teams\/1483.png"},"statistics":[{"type":"Shots on Goal","value":3},{"type":"Shots off Goal","value":2},{"type":"Total Shots","value":7},{"type":"Blocked Shots","value":2},{"type":"Shots insidebox","value":6},{"type":"Shots outsidebox","value":1},{"type":"Fouls","value":13},{"type":"Corner Kicks","value":2},{"type":"Offsides","value":null},{"type":"Ball Possession","value":"41%"},{"type":"Yellow Cards","value":1},{"type":"Red Cards","value":1},{"type":"Goalkeeper Saves","value":2},{"type":"Total passes","value":331},{"type":"Passes accurate","value":249},{"type":"Passes %","value":"75%"},{"type":"expected_goals","value":"1.57"}]}],"players":[{"team":{"id":561,"name":"HNK Rijeka","logo":"https:\/\/media.api-sports.io\/football\/teams\/561.png","update":"2024-05-14T04:20:03+00:00"},"players":[{"player":{"id":14553,"name":"Nediljko Labrovi\u0107","photo":"https:\/\/media.api-sports.io\/football\/players\/14553.png"},"statistics":[{"games":{"minutes":90,"number":1,"position":"G","rating":"6.6","captain":false,"substitute":false},"offsides":null,"shots":{"total":null,"on":null},"goals":{"total":null,"conceded":2,"assists":null,"saves":1},"passes":{"total":23,"key":null,"accuracy":"21"},"tackles":{"total":null,"blocks":null,"interceptions":null},"duels":{"total":null,"won":null},"dribbles":{"attempts":null,"success":null,"past":null},"fouls":{"drawn":null,"committed":null},"cards":{"yellow":0,"red":0},"penalty":{"won":null,"commited":null,"scored":0,"missed":0,"saved":0}}]},{"player":{"id":14266,"name":"Ivan Smol\u010di\u0107","photo":"https:\/\/media.api-sports.io\/football\/players\/14266.png"},"statistics":[{"games":{"minutes":90,"number":28,"position":"D","rating":"7","captain":false,"substitute":false},"offsides":null,"shots":{"total":1,"on":null},"goals":{"total":null,"conceded":0,"assists":null,"saves":null},"passes":{"total":37,"key":2,"accuracy":"30"},"tackles":{"total":null,"blocks":null,"interceptions":1},"duels":{"total":4,"won":2},"dribbles":{"attempts":null,"success":null,"past":null},"fouls":{"drawn":2,"committed":2},"cards":{"yellow":0,"red":0},"penalty":{"won":null,"commited":null,"scored":0,"missed":0,"saved":null}}]},{"player":{"id":263476,"name":"Niko Gale\u0161i\u0107","photo":"https:\/\/media.api-sports.io\/football\/players\/263476.png"},"statistics":[{"games":{"minutes":90,"number":5,"position":"D","rating":"7.2","captain":false,"substitute":false},"offsides":null,"shots":{"total":2,"on":2},"goals":{"total":null,"conceded":0,"assists":null,"saves":null},"passes":{"total":65,"key":null,"accuracy":"54"},"tackles":{"total":1,"blocks":1,"interceptions":null},"duels":{"total":2,"won":2},"dribbles":{"attempts":null,"success":null,"past":null},"fouls":{"drawn":1,"committed":null},"cards":{"yellow":0,"red":0},"penalty":{"won":null,"commited":null,"scored":0,"missed":0,"saved":null}}]},{"player":{"id":70,"name":"Matej Mitrovi\u0107","photo":"https:\/\/media.api-sports.io\/football\/players\/70.png"},"statistics":[{"games":{"minutes":90,"number":6,"position":"D","rating":"6","captain":false,"substitute":false},"offsides":null,"shots":{"total":null,"on":null},"goals":{"total":null,"conceded":0,"assists":null,"saves":null},"passes":{"total":74,"key":null,"accuracy":"64"},"tackles":{"total":null,"blocks":null,"interceptions":1},"duels":{"total":1,"won":null},"dribbles":{"attempts":null,"success":null,"past":null},"fouls":{"drawn":null,"committed":1},"cards":{"yellow":1,"red":0},"penalty":{"won":null,"commited":1,"scored":0,"missed":0,"saved":null}}]},{"player":{"id":14410,"name":"Bruno Goda","photo":"https:\/\/media.api-sports.io\/football\/players\/14410.png"},"statistics":[{"games":{"minutes":90,"number":3,"position":"D","rating":"6.9","captain":false,"substitute":false},"offsides":null,"shots":{"total":null,"on":null},"goals":{"total":null,"conceded":0,"assists":null,"saves":null},"passes":{"total":55,"key":1,"accuracy":"42"},"tackles":{"total":null,"blocks":null,"interceptions":1},"duels":{"total":8,"won":6},"dribbles":{"attempts":null,"success":null,"past":1},"fouls":{"drawn":4,"committed":1},"cards":{"yellow":0,"red":0},"penalty":{"won":null,"commited":null,"scored":0,"missed":0,"saved":null}}]},{"player":{"id":108453,"name":"Lindon Selahi","photo":"https:\/\/media.api-sports.io\/football\/players\/108453.png"},"statistics":[{"games":{"minutes":59,"number":18,"position":"M","rating":"6.7","captain":false,"substitute":false},"offsides":null,"shots":{"total":null,"on":null},"goals":{"total":null,"conceded":0,"assists":null,"saves":null},"passes":{"total":19,"key":1,"accuracy":"14"},"tackles":{"total":null,"blocks":null,"interceptions":null},"duels":{"total":2,"won":null},"dribbles":{"attempts":null,"success":null,"past":null},"fouls":{"drawn":null,"committed":1},"cards":{"yellow":0,"red":0},"penalty":{"won":null,"commited":null,"scored":0,"missed":0,"saved":null}}]},{"player":{"id":135957,"name":"Veldin Hod\u017ea","photo":"https:\/\/media.api-sports.io\/football\/players\/135957.png"},"statistics":[{"games":{"minutes":78,"number":25,"position":"M","rating":"6.5","captain":false,"substitute":false},"offsides":null,"shots":{"total":null,"on":null},"goals":{"total":null,"conceded":0,"assists":null,"saves":null},"passes":{"total":30,"key":null,"accuracy":"29"},"tackles":{"total":1,"blocks":null,"interceptions":null},"duels":{"total":5,"won":1},"dribbles":{"attempts":null,"success":null,"past":null},"fouls":{"drawn":null,"committed":4},"cards":{"yellow":1,"red":0},"penalty":{"won":null,"commited":null,"scored":0,"missed":0,"saved":null}}]},{"player":{"id":260865,"name":"Marco Pa\u0161ali\u0107","photo":"https:\/\/media.api-sports.io\/football\/players\/260865.png"},"statistics":[{"games":{"minutes":72,"number":87,"position":"M","rating":"7.2","captain":false,"substitute":false},"offsides":null,"shots":{"total":2,"on":null},"goals":{"total":null,"conceded":0,"assists":null,"saves":null},"passes":{"total":18,"key":2,"accuracy":"12"},"tackles":{"total":1,"blocks":null,"interceptions":null},"duels":{"total":3,"won":2},"dribbles":{"attempts":1,"success":1,"past":null},"fouls":{"drawn":null,"committed":null},"cards":{"yellow":0,"red":0},"penalty":{"won":null,"commited":null,"scored":0,"missed":0,"saved":null}}]},{"player":{"id":284869,"name":"Toni Fruk","photo":"https:\/\/media.api-sports.io\/football\/players\/284869.png"},"statistics":[{"games":{"minutes":78,"number":21,"position":"M","rating":"6.9","captain":false,"substitute":false},"offsides":null,"shots":{"total":1,"on":null},"goals":{"total":null,"conceded":0,"assists":1,"saves":null},"passes":{"total":38,"key":3,"accuracy":"28"},"tackles":{"total":3,"blocks":1,"interceptions":2},"duels":{"total":12,"won":5},"dribbles":{"attempts":3,"success":1,"past":null},"fouls":{"drawn":null,"committed":null},"cards":{"yellow":0,"red":0},"penalty":{"won":null,"commited":null,"scored":0,"missed":0,"saved":null}}]},{"player":{"id":14705,"name":"Niko Jankovi\u0107","photo":"https:\/\/media.api-sports.io\/football\/players\/14705.png"},"statistics":[{"games":{"minutes":90,"number":4,"position":"M","rating":"7.9","captain":false,"substitute":false},"offsides":null,"shots":{"total":6,"on":1},"goals":{"total":1,"conceded":0,"assists":null,"saves":null},"passes":{"total":34,"key":null,"accuracy":"21"},"tackles":{"total":1,"blocks":null,"interceptions":null},"duels":{"total":9,"won":5},"dribbles":{"attempts":3,"success":2,"past":null},"fouls":{"drawn":2,"committed":2},"cards":{"yellow":1,"red":0},"penalty":{"won":null,"commited":null,"scored":0,"missed":0,"saved":null}}]},{"player":{"id":202951,"name":"Franjo Ivanovi\u0107","photo":"https:\/\/media.api-sports.io\/football\/players\/202951.png"},"statistics":[{"games":{"minutes":59,"number":89,"position":"F","rating":"7","captain":false,"substitute":false},"offsides":null,"shots":{"total":1,"on":null},"goals":{"total":null,"conceded":0,"assists":null,"saves":null},"passes":{"total":14,"key":1,"accuracy":"10"},"tackles":{"total":null,"blocks":null,"interceptions":null},"duels":{"total":8,"won":4},"dribbles":{"attempts":2,"success":1,"past":1},"fouls":{"drawn":3,"committed":1},"cards":{"yellow":0,"red":0},"penalty":{"won":null,"commited":null,"scored":0,"missed":0,"saved":null}}]},{"player":{"id":215840,"name":"Silvio Ilinkovi\u0107","photo":"https:\/\/media.api-sports.io\/football\/players\/215840.png"},"statistics":[{"games":{"minutes":31,"number":27,"position":"M","rating":"6.3","captain":false,"substitute":true},"offsides":null,"shots":{"total":null,"on":null},"goals":{"total":null,"conceded":0,"assists":null,"saves":null},"passes":{"total":16,"key":null,"accuracy":"12"},"tackles":{"total":null,"blocks":null,"interceptions":null},"duels":{"total":null,"won":null},"dribbles":{"attempts":null,"success":null,"past":null},"fouls":{"drawn":null,"committed":null},"cards":{"yellow":0,"red":0},"penalty":{"won":null,"commited":null,"scored":0,"missed":0,"saved":null}}]},{"player":{"id":30413,"name":"Marko Pjaca","photo":"https:\/\/media.api-sports.io\/football\/players\/30413.png"},"statistics":[{"games":{"minutes":31,"number":20,"position":"M","rating":"6.3","captain":false,"substitute":true},"offsides":null,"shots":{"total":null,"on":null},"goals":{"total":null,"conceded":0,"assists":null,"saves":null},"passes":{"total":7,"key":1,"accuracy":"6"},"tackles":{"total":null,"blocks":null,"interceptions":null},"duels":{"total":1,"won":1},"dribbles":{"attempts":1,"success":1,"past":null},"fouls":{"drawn":null,"committed":null},"cards":{"yellow":0,"red":0},"penalty":{"won":null,"commited":null,"scored":0,"missed":0,"saved":null}}]},{"player":{"id":13554,"name":"Jorge Obreg\u00f3n","photo":"https:\/\/media.api-sports.io\/football\/players\/13554.png"},"statistics":[{"games":{"minutes":18,"number":9,"position":"M","rating":"7.5","captain":false,"substitute":true},"offsides":null,"shots":{"total":2,"on":1},"goals":{"total":1,"conceded":0,"assists":null,"saves":null},"passes":{"total":5,"key":1,"accuracy":"4"},"tackles":{"total":null,"blocks":null,"interceptions":null},"duels":{"total":2,"won":1},"dribbles":{"attempts":null,"success":null,"past":null},"fouls":{"drawn":1,"committed":null},"cards":{"yellow":0,"red":0},"penalty":{"won":null,"commited":null,"scored":0,"missed":0,"saved":null}}]},{"player":{"id":14308,"name":"Alen Grgi\u0107","photo":"https:\/\/media.api-sports.io\/football\/players\/14308.png"},"statistics":[{"games":{"minutes":12,"number":23,"position":"D","rating":"6.6","captain":false,"substitute":true},"offsides":null,"shots":{"total":null,"on":null},"goals":{"total":null,"conceded":0,"assists":null,"saves":null},"passes":{"total":8,"key":1,"accuracy":"4"},"tackles":{"total":null,"blocks":null,"interceptions":null},"duels":{"total":1,"won":null},"dribbles":{"attempts":null,"success":null,"past":null},"fouls":{"drawn":null,"committed":null},"cards":{"yellow":0,"red":0},"penalty":{"won":null,"commited":null,"scored":0,"missed":0,"saved":null}}]},{"player":{"id":21033,"name":"Emmanuel Banda","photo":"https:\/\/media.api-sports.io\/football\/players\/21033.png"},"statistics":[{"games":{"minutes":12,"number":22,"position":"M","rating":"6.6","captain":false,"substitute":true},"offsides":null,"shots":{"total":null,"on":null},"goals":{"total":null,"conceded":0,"assists":null,"saves":null},"passes":{"total":12,"key":1,"accuracy":"8"},"tackles":{"total":null,"blocks":null,"interceptions":null},"duels":{"total":null,"won":null},"dribbles":{"attempts":null,"success":null,"past":null},"fouls":{"drawn":null,"committed":null},"cards":{"yellow":0,"red":0},"penalty":{"won":null,"commited":null,"scored":0,"missed":0,"saved":null}}]},{"player":{"id":108370,"name":"Martin Zlomisli\u0107","photo":"https:\/\/media.api-sports.io\/football\/players\/108370.png"},"statistics":[{"games":{"minutes":null,"number":13,"position":"G","rating":null,"captain":false,"substitute":true},"offsides":null,"shots":{"total":null,"on":null},"goals":{"total":null,"conceded":0,"assists":null,"saves":null},"passes":{"total":null,"key":null,"accuracy":null},"tackles":{"total":null,"blocks":null,"interceptions":null},"duels":{"total":null,"won":null},"dribbles":{"attempts":null,"success":null,"past":null},"fouls":{"drawn":null,"committed":null},"cards":{"yellow":0,"red":0},"penalty":{"won":null,"commited":null,"scored":0,"missed":0,"saved":null}}]},{"player":{"id":1307,"name":"Emir Dilaver","photo":"https:\/\/media.api-sports.io\/football\/players\/1307.png"},"statistics":[{"games":{"minutes":null,"number":66,"position":"D","rating":null,"captain":false,"substitute":true},"offsides":null,"shots":{"total":null,"on":null},"goals":{"total":null,"conceded":0,"assists":null,"saves":null},"passes":{"total":null,"key":null,"accuracy":null},"tackles":{"total":null,"blocks":null,"interceptions":null},"duels":{"total":null,"won":null},"dribbles":{"attempts":null,"success":null,"past":null},"fouls":{"drawn":null,"committed":null},"cards":{"yellow":0,"red":0},"penalty":{"won":null,"commited":null,"scored":0,"missed":0,"saved":null}}]},{"player":{"id":161702,"name":"Danilo Veiga","photo":"https:\/\/media.api-sports.io\/football\/players\/161702.png"},"statistics":[{"games":{"minutes":null,"number":77,"position":"D","rating":null,"captain":false,"substitute":true},"offsides":null,"shots":{"total":null,"on":null},"goals":{"total":null,"conceded":0,"assists":null,"saves":null},"passes":{"total":null,"key":null,"accuracy":null},"tackles":{"total":null,"blocks":null,"interceptions":null},"duels":{"total":null,"won":null},"dribbles":{"attempts":null,"success":null,"past":null},"fouls":{"drawn":null,"committed":null},"cards":{"yellow":0,"red":0},"penalty":{"won":null,"commited":null,"scored":0,"missed":0,"saved":null}}]},{"player":{"id":14358,"name":"Marijan \u010cabraja","photo":"https:\/\/media.api-sports.io\/football\/players\/14358.png"},"statistics":[{"games":{"minutes":null,"number":32,"position":"D","rating":null,"captain":false,"substitute":true},"offsides":null,"shots":{"total":null,"on":null},"goals":{"total":null,"conceded":0,"assists":null,"saves":null},"passes":{"total":null,"key":null,"accuracy":null},"tackles":{"total":null,"blocks":null,"interceptions":null},"duels":{"total":null,"won":null},"dribbles":{"attempts":null,"success":null,"past":null},"fouls":{"drawn":null,"committed":null},"cards":{"yellow":0,"red":0},"penalty":{"won":null,"commited":null,"scored":0,"missed":0,"saved":null}}]},{"player":{"id":14286,"name":"Adrian Liber","photo":"https:\/\/media.api-sports.io\/football\/players\/14286.png"},"statistics":[{"games":{"minutes":null,"number":8,"position":"M","rating":null,"captain":false,"substitute":true},"offsides":null,"shots":{"total":null,"on":null},"goals":{"total":null,"conceded":0,"assists":null,"saves":null},"passes":{"total":null,"key":null,"accuracy":null},"tackles":{"total":null,"blocks":null,"interceptions":null},"duels":{"total":null,"won":null},"dribbles":{"attempts":null,"success":null,"past":null},"fouls":{"drawn":null,"committed":null},"cards":{"yellow":0,"red":0},"penalty":{"won":null,"commited":null,"scored":0,"missed":0,"saved":null}}]},{"player":{"id":14285,"name":"Ivan Lepinjica","photo":"https:\/\/media.api-sports.io\/football\/players\/14285.png"},"statistics":[{"games":{"minutes":null,"number":12,"position":"M","rating":null,"captain":false,"substitute":true},"offsides":null,"shots":{"total":null,"on":null},"goals":{"total":null,"conceded":0,"assists":null,"saves":null},"passes":{"total":null,"key":null,"accuracy":null},"tackles":{"total":null,"blocks":null,"interceptions":null},"duels":{"total":null,"won":null},"dribbles":{"attempts":null,"success":null,"past":null},"fouls":{"drawn":null,"committed":null},"cards":{"yellow":0,"red":0},"penalty":{"won":null,"commited":null,"scored":0,"missed":0,"saved":null}}]},{"player":{"id":14428,"name":"Bruno Bogojevi\u0107","photo":"https:\/\/media.api-sports.io\/football\/players\/14428.png"},"statistics":[{"games":{"minutes":null,"number":30,"position":"F","rating":null,"captain":false,"substitute":true},"offsides":null,"shots":{"total":null,"on":null},"goals":{"total":null,"conceded":0,"assists":null,"saves":null},"passes":{"total":null,"key":null,"accuracy":null},"tackles":{"total":null,"blocks":null,"interceptions":null},"duels":{"total":null,"won":null},"dribbles":{"attempts":null,"success":null,"past":null},"fouls":{"drawn":null,"committed":null},"cards":{"yellow":0,"red":0},"penalty":{"won":null,"commited":null,"scored":0,"missed":0,"saved":null}}]}]},{"team":{"id":1483,"name":"NK Varazdin","logo":"https:\/\/media.api-sports.io\/football\/teams\/1483.png","update":"2024-05-14T04:20:03+00:00"},"players":[{"player":{"id":37361,"name":"Oliver Zelenika","photo":"https:\/\/media.api-sports.io\/football\/players\/37361.png"},"statistics":[{"games":{"minutes":90,"number":1,"position":"G","rating":"6.6","captain":false,"substitute":false},"offsides":null,"shots":{"total":null,"on":null},"goals":{"total":null,"conceded":2,"assists":null,"saves":2},"passes":{"total":53,"key":null,"accuracy":"32"},"tackles":{"total":null,"blocks":null,"interceptions":null},"duels":{"total":null,"won":null},"dribbles":{"attempts":null,"success":null,"past":null},"fouls":{"drawn":null,"committed":null},"cards":{"yellow":1,"red":0},"penalty":{"won":null,"commited":null,"scored":0,"missed":0,"saved":0}}]},{"player":{"id":29998,"name":"Marko Vuk\u010devi\u0107","photo":"https:\/\/media.api-sports.io\/football\/players\/29998.png"},"statistics":[{"games":{"minutes":90,"number":19,"position":"D","rating":"6.3","captain":false,"substitute":false},"offsides":null,"shots":{"total":null,"on":null},"goals":{"total":null,"conceded":0,"assists":null,"saves":null},"passes":{"total":30,"key":null,"accuracy":"21"},"tackles":{"total":2,"blocks":null,"interceptions":1},"duels":{"total":7,"won":3},"dribbles":{"attempts":null,"success":null,"past":2},"fouls":{"drawn":1,"committed":2},"cards":{"yellow":0,"red":0},"penalty":{"won":null,"commited":null,"scored":0,"missed":0,"saved":null}}]},{"player":{"id":79944,"name":"Luka Jeleni\u0107","photo":"https:\/\/media.api-sports.io\/football\/players\/79944.png"},"statistics":[{"games":{"minutes":58,"number":26,"position":"D","rating":"6.7","captain":false,"substitute":false},"offsides":null,"shots":{"total":null,"on":null},"goals":{"total":null,"conceded":0,"assists":null,"saves":null},"passes":{"total":33,"key":null,"accuracy":"28"},"tackles":{"total":1,"blocks":null,"interceptions":null},"duels":{"total":4,"won":2},"dribbles":{"attempts":1,"success":1,"past":null},"fouls":{"drawn":null,"committed":1},"cards":{"yellow":0,"red":0},"penalty":{"won":null,"commited":null,"scored":0,"missed":0,"saved":null}}]},{"player":{"id":3605,"name":"Jorgo P\u00ebllumbi","photo":"https:\/\/media.api-sports.io\/football\/players\/3605.png"},"statistics":[{"games":{"minutes":83,"number":4,"position":"D","rating":"6.3","captain":false,"substitute":false},"offsides":null,"shots":{"total":1,"on":null},"goals":{"total":null,"conceded":0,"assists":null,"saves":null},"passes":{"total":31,"key":null,"accuracy":"27"},"tackles":{"total":null,"blocks":2,"interceptions":1},"duels":{"total":2,"won":null},"dribbles":{"attempts":null,"success":null,"past":null},"fouls":{"drawn":null,"committed":2},"cards":{"yellow":0,"red":1},"penalty":{"won":null,"commited":null,"scored":0,"missed":0,"saved":null}}]},{"player":{"id":33387,"name":"Karlo Bru\u010di\u0107","photo":"https:\/\/media.api-sports.io\/football\/players\/33387.png"},"statistics":[{"games":{"minutes":90,"number":3,"position":"D","rating":"6.3","captain":false,"substitute":false},"offsides":null,"shots":{"total":null,"on":null},"goals":{"total":null,"conceded":0,"assists":null,"saves":null},"passes":{"total":24,"key":null,"accuracy":"22"},"tackles":{"total":null,"blocks":null,"interceptions":1},"duels":{"total":2,"won":null},"dribbles":{"attempts":1,"success":null,"past":1},"fouls":{"drawn":null,"committed":null},"cards":{"yellow":0,"red":0},"penalty":{"won":null,"commited":null,"scored":0,"missed":0,"saved":null}}]},{"player":{"id":14457,"name":"Igor Postonjski","photo":"https:\/\/media.api-sports.io\/football\/players\/14457.png"},"statistics":[{"games":{"minutes":80,"number":8,"position":"M","rating":"7.6","captain":false,"substitute":false},"offsides":null,"shots":{"total":1,"on":1},"goals":{"total":1,"conceded":0,"assists":null,"saves":null},"passes":{"total":33,"key":null,"accuracy":"29"},"tackles":{"total":1,"blocks":3,"interceptions":1},"duels":{"total":6,"won":4},"dribbles":{"attempts":null,"success":null,"past":null},"fouls":{"drawn":2,"committed":2},"cards":{"yellow":0,"red":0},"penalty":{"won":null,"commited":null,"scored":1,"missed":0,"saved":null}}]},{"player":{"id":146044,"name":"Agon Elezi","photo":"https:\/\/media.api-sports.io\/football\/players\/146044.png"},"statistics":[{"games":{"minutes":90,"number":22,"position":"M","rating":"6.6","captain":false,"substitute":false},"offsides":null,"shots":{"total":null,"on":null},"goals":{"total":null,"conceded":0,"assists":null,"saves":null},"passes":{"total":41,"key":null,"accuracy":"33"},"tackles":{"total":3,"blocks":null,"interceptions":1},"duels":{"total":9,"won":4},"dribbles":{"attempts":1,"success":null,"past":1},"fouls":{"drawn":1,"committed":2},"cards":{"yellow":0,"red":0},"penalty":{"won":null,"commited":null,"scored":0,"missed":0,"saved":null}}]},{"player":{"id":163483,"name":"Dimitar Mitrovski","photo":"https:\/\/media.api-sports.io\/football\/players\/163483.png"},"statistics":[{"games":{"minutes":80,"number":17,"position":"M","rating":"7","captain":false,"substitute":false},"offsides":null,"shots":{"total":null,"on":null},"goals":{"total":null,"conceded":0,"assists":1,"saves":null},"passes":{"total":19,"key":2,"accuracy":"15"},"tackles":{"total":3,"blocks":null,"interceptions":null},"duels":{"total":11,"won":5},"dribbles":{"attempts":1,"success":1,"past":null},"fouls":{"drawn":1,"committed":2},"cards":{"yellow":0,"red":0},"penalty":{"won":null,"commited":null,"scored":0,"missed":0,"saved":null}}]},{"player":{"id":295976,"name":"Leon Belcar","photo":"https:\/\/media.api-sports.io\/football\/players\/295976.png"},"statistics":[{"games":{"minutes":45,"number":10,"position":"M","rating":"6.6","captain":false,"substitute":false},"offsides":null,"shots":{"total":null,"on":null},"goals":{"total":null,"conceded":0,"assists":null,"saves":null},"passes":{"total":8,"key":1,"accuracy":"6"},"tackles":{"total":1,"blocks":null,"interceptions":null},"duels":{"total":2,"won":1},"dribbles":{"attempts":1,"success":null,"past":null},"fouls":{"drawn":null,"committed":null},"cards":{"yellow":0,"red":0},"penalty":{"won":null,"commited":null,"scored":0,"missed":0,"saved":null}}]},{"player":{"id":14352,"name":"Michele \u0160ego","photo":"https:\/\/media.api-sports.io\/football\/players\/14352.png"},"statistics":[{"games":{"minutes":90,"number":11,"position":"M","rating":"6.6","captain":false,"substitute":false},"offsides":null,"shots":{"total":null,"on":null},"goals":{"total":null,"conceded":0,"assists":null,"saves":null},"passes":{"total":20,"key":null,"accuracy":"13"},"tackles":{"total":1,"blocks":null,"interceptions":2},"duels":{"total":6,"won":4},"dribbles":{"attempts":null,"success":null,"past":1},"fouls":{"drawn":3,"committed":1},"cards":{"yellow":0,"red":0},"penalty":{"won":null,"commited":null,"scored":0,"missed":0,"saved":null}}]},{"player":{"id":30904,"name":"Fran Brodi\u0107","photo":"https:\/\/media.api-sports.io\/football\/players\/30904.png"},"statistics":[{"games":{"minutes":86,"number":7,"position":"F","rating":"7.3","captain":false,"substitute":false},"offsides":null,"shots":{"total":3,"on":2},"goals":{"total":1,"conceded":0,"assists":null,"saves":null},"passes":{"total":16,"key":null,"accuracy":"11"},"tackles":{"total":null,"blocks":null,"interceptions":null},"duels":{"total":5,"won":3},"dribbles":{"attempts":null,"success":null,"past":null},"fouls":{"drawn":3,"committed":1},"cards":{"yellow":0,"red":0},"penalty":{"won":1,"commited":null,"scored":0,"missed":0,"saved":null}}]},{"player":{"id":90736,"name":"Ante Vuku\u0161i\u0107","photo":"https:\/\/media.api-sports.io\/football\/players\/90736.png"},"statistics":[{"games":{"minutes":45,"number":30,"position":"F","rating":"6.3","captain":false,"substitute":true},"offsides":null,"shots":{"total":null,"on":null},"goals":{"total":null,"conceded":0,"assists":null,"saves":null},"passes":{"total":6,"key":null,"accuracy":"4"},"tackles":{"total":null,"blocks":null,"interceptions":null},"duels":{"total":null,"won":null},"dribbles":{"attempts":null,"success":null,"past":null},"fouls":{"drawn":null,"committed":null},"cards":{"yellow":0,"red":0},"penalty":{"won":null,"commited":null,"scored":0,"missed":0,"saved":null}}]},{"player":{"id":14445,"name":"Ivan Neki\u0107","photo":"https:\/\/media.api-sports.io\/football\/players\/14445.png"},"statistics":[{"games":{"minutes":32,"number":6,"position":"D","rating":"6.9","captain":false,"substitute":true},"offsides":null,"shots":{"total":null,"on":null},"goals":{"total":null,"conceded":0,"assists":null,"saves":null},"passes":{"total":13,"key":null,"accuracy":"7"},"tackles":{"total":2,"blocks":1,"interceptions":1},"duels":{"total":3,"won":3},"dribbles":{"attempts":null,"success":null,"past":null},"fouls":{"drawn":1,"committed":null},"cards":{"yellow":0,"red":0},"penalty":{"won":null,"commited":null,"scored":0,"missed":0,"saved":null}}]},{"player":{"id":215929,"name":"Luka \u0160kari\u010di\u0107","photo":"https:\/\/media.api-sports.io\/football\/players\/215929.png"},"statistics":[{"games":{"minutes":10,"number":28,"position":"D","rating":"6.3","captain":false,"substitute":true},"offsides":null,"shots":{"total":null,"on":null},"goals":{"total":null,"conceded":0,"assists":null,"saves":null},"passes":{"total":null,"key":null,"accuracy":null},"tackles":{"total":null,"blocks":1,"interceptions":null},"duels":{"total":null,"won":null},"dribbles":{"attempts":null,"success":null,"past":null},"fouls":{"drawn":null,"committed":null},"cards":{"yellow":0,"red":0},"penalty":{"won":null,"commited":null,"scored":0,"missed":0,"saved":null}}]},{"player":{"id":125702,"name":"David Mistrafovi\u0107","photo":"https:\/\/media.api-sports.io\/football\/players\/125702.png"},"statistics":[{"games":{"minutes":10,"number":20,"position":"M","rating":"6.2","captain":false,"substitute":true},"offsides":null,"shots":{"total":null,"on":null},"goals":{"total":null,"conceded":0,"assists":null,"saves":null},"passes":{"total":4,"key":null,"accuracy":"1"},"tackles":{"total":null,"blocks":null,"interceptions":null},"duels":{"total":null,"won":null},"dribbles":{"attempts":null,"success":null,"past":null},"fouls":{"drawn":null,"committed":null},"cards":{"yellow":0,"red":0},"penalty":{"won":null,"commited":null,"scored":0,"missed":0,"saved":null}}]},{"player":{"id":328631,"name":"Lovro Banovec","photo":"https:\/\/media.api-sports.io\/football\/players\/328631.png"},"statistics":[{"games":{"minutes":13,"number":15,"position":"M","rating":"6.3","captain":false,"substitute":true},"offsides":null,"shots":{"total":null,"on":null},"goals":{"total":null,"conceded":0,"assists":null,"saves":null},"passes":{"total":null,"key":null,"accuracy":null},"tackles":{"total":null,"blocks":null,"interceptions":null},"duels":{"total":1,"won":null},"dribbles":{"attempts":null,"success":null,"past":1},"fouls":{"drawn":null,"committed":null},"cards":{"yellow":0,"red":0},"penalty":{"won":null,"commited":null,"scored":0,"missed":0,"saved":null}}]},{"player":{"id":14610,"name":"Josip Silic","photo":"https:\/\/media.api-sports.io\/football\/players\/14610.png"},"statistics":[{"games":{"minutes":null,"number":12,"position":"G","rating":null,"captain":false,"substitute":true},"offsides":null,"shots":{"total":null,"on":null},"goals":{"total":null,"conceded":0,"assists":null,"saves":null},"passes":{"total":null,"key":null,"accuracy":null},"tackles":{"total":null,"blocks":null,"interceptions":null},"duels":{"total":null,"won":null},"dribbles":{"attempts":null,"success":null,"past":null},"fouls":{"drawn":null,"committed":null},"cards":{"yellow":0,"red":0},"penalty":{"won":null,"commited":null,"scored":0,"missed":0,"saved":null}}]},{"player":{"id":14508,"name":"Antonio Bor\u0161i\u0107","photo":"https:\/\/media.api-sports.io\/football\/players\/14508.png"},"statistics":[{"games":{"minutes":null,"number":25,"position":"D","rating":null,"captain":false,"substitute":true},"offsides":null,"shots":{"total":null,"on":null},"goals":{"total":null,"conceded":0,"assists":null,"saves":null},"passes":{"total":null,"key":null,"accuracy":null},"tackles":{"total":null,"blocks":null,"interceptions":null},"duels":{"total":null,"won":null},"dribbles":{"attempts":null,"success":null,"past":null},"fouls":{"drawn":null,"committed":null},"cards":{"yellow":0,"red":0},"penalty":{"won":null,"commited":null,"scored":0,"missed":0,"saved":null}}]},{"player":{"id":283707,"name":"Karlo Lusavec","photo":"https:\/\/media.api-sports.io\/football\/players\/283707.png"},"statistics":[{"games":{"minutes":null,"number":14,"position":"M","rating":null,"captain":false,"substitute":true},"offsides":null,"shots":{"total":null,"on":null},"goals":{"total":null,"conceded":0,"assists":null,"saves":null},"passes":{"total":null,"key":null,"accuracy":null},"tackles":{"total":null,"blocks":null,"interceptions":null},"duels":{"total":null,"won":null},"dribbles":{"attempts":null,"success":null,"past":null},"fouls":{"drawn":null,"committed":null},"cards":{"yellow":0,"red":0},"penalty":{"won":null,"commited":null,"scored":0,"missed":0,"saved":null}}]},{"player":{"id":14400,"name":"Domagoj Dro\u017e\u0111ek","photo":"https:\/\/media.api-sports.io\/football\/players\/14400.png"},"statistics":[{"games":{"minutes":null,"number":9,"position":"F","rating":null,"captain":false,"substitute":true},"offsides":null,"shots":{"total":null,"on":null},"goals":{"total":null,"conceded":0,"assists":null,"saves":null},"passes":{"total":null,"key":null,"accuracy":null},"tackles":{"total":null,"blocks":null,"interceptions":null},"duels":{"total":null,"won":null},"dribbles":{"attempts":null,"success":null,"past":null},"fouls":{"drawn":null,"committed":null},"cards":{"yellow":0,"red":0},"penalty":{"won":null,"commited":null,"scored":0,"missed":0,"saved":null}}]},{"player":{"id":14549,"name":"Leonard Vuk","photo":"https:\/\/media.api-sports.io\/football\/players\/14549.png"},"statistics":[{"games":{"minutes":null,"number":13,"position":"M","rating":null,"captain":false,"substitute":true},"offsides":null,"shots":{"total":null,"on":null},"goals":{"total":null,"conceded":0,"assists":null,"saves":null},"passes":{"total":null,"key":null,"accuracy":null},"tackles":{"total":null,"blocks":null,"interceptions":null},"duels":{"total":null,"won":null},"dribbles":{"attempts":null,"success":null,"past":null},"fouls":{"drawn":null,"committed":null},"cards":{"yellow":0,"red":0},"penalty":{"won":null,"commited":null,"scored":0,"missed":0,"saved":null}}]},{"player":{"id":337626,"name":"Niko Domjani\u0107","photo":"https:\/\/media.api-sports.io\/football\/players\/337626.png"},"statistics":[{"games":{"minutes":null,"number":29,"position":"F","rating":null,"captain":false,"substitute":true},"offsides":null,"shots":{"total":null,"on":null},"goals":{"total":null,"conceded":0,"assists":null,"saves":null},"passes":{"total":null,"key":null,"accuracy":null},"tackles":{"total":null,"blocks":null,"interceptions":null},"duels":{"total":null,"won":null},"dribbles":{"attempts":null,"success":null,"past":null},"fouls":{"drawn":null,"committed":null},"cards":{"yellow":0,"red":0},"penalty":{"won":null,"commited":null,"scored":0,"missed":0,"saved":null}}]},{"player":{"id":326627,"name":"Noa Vugrinec","photo":"https:\/\/media.api-sports.io\/football\/players\/326627.png"},"statistics":[{"games":{"minutes":null,"number":16,"position":"F","rating":null,"captain":false,"substitute":true},"offsides":null,"shots":{"total":null,"on":null},"goals":{"total":null,"conceded":0,"assists":null,"saves":null},"passes":{"total":null,"key":null,"accuracy":null},"tackles":{"total":null,"blocks":null,"interceptions":null},"duels":{"total":null,"won":null},"dribbles":{"attempts":null,"success":null,"past":null},"fouls":{"drawn":null,"committed":null},"cards":{"yellow":0,"red":0},"penalty":{"won":null,"commited":null,"scored":0,"missed":0,"saved":null}}]}]}]}]}