{"get":"players","parameters":{"season":"2023","league":"210","page":"18"},"errors":[],"results":20,"paging":{"current":18,"total":28},"response":[{"player":{"id":14295,"name":"J. Mitrovi\u0107","firstname":"Josip","lastname":"Mitrovi\u0107","age":24,"birth":{"date":"2000-06-11","place":"Osijek","country":"Croatia"},"nationality":"Croatia","height":"174 cm","weight":"74 kg","injured":false,"photo":"https:\/\/media.api-sports.io\/football\/players\/14295.png"},"statistics":[{"team":{"id":1068,"name":"HNK Gorica","logo":"https:\/\/media.api-sports.io\/football\/teams\/1068.png"},"league":{"id":210,"name":"HNL","country":"Croatia","logo":"https:\/\/media.api-sports.io\/football\/leagues\/210.png","flag":"https:\/\/media.api-sports.io\/flags\/hr.svg","season":2023},"games":{"appearences":31,"lineups":29,"minutes":2353,"number":null,"position":"Attacker","rating":"7.057142","captain":false},"substitutes":{"in":2,"out":23,"bench":2},"shots":{"total":29,"on":10},"goals":{"total":3,"conceded":0,"assists":3,"saves":null},"passes":{"total":414,"key":18,"accuracy":13},"tackles":{"total":32,"blocks":3,"interceptions":14},"duels":{"total":229,"won":110},"dribbles":{"attempts":54,"success":24,"past":null},"fouls":{"drawn":41,"committed":27},"cards":{"yellow":3,"yellowred":0,"red":0},"penalty":{"won":null,"commited":null,"scored":0,"missed":0,"saved":null}}]},{"player":{"id":14354,"name":"I. \u010covi\u0107","firstname":"Ivan","lastname":"\u010covi\u0107","age":34,"birth":{"date":"1990-09-17","place":"Zagreb","country":"Croatia"},"nationality":"Croatia","height":"194 cm","weight":"89 kg","injured":false,"photo":"https:\/\/media.api-sports.io\/football\/players\/14354.png"},"statistics":[{"team":{"id":1018,"name":"NK Slaven Belupo","logo":"https:\/\/media.api-sports.io\/football\/teams\/1018.png"},"league":{"id":210,"name":"HNL","country":"Croatia","logo":"https:\/\/media.api-sports.io\/football\/leagues\/210.png","flag":"https:\/\/media.api-sports.io\/flags\/hr.svg","season":2023},"games":{"appearences":1,"lineups":1,"minutes":90,"number":null,"position":"Goalkeeper","rating":"6.000000","captain":false},"substitutes":{"in":0,"out":0,"bench":23},"shots":{"total":null,"on":null},"goals":{"total":0,"conceded":4,"assists":null,"saves":2},"passes":{"total":29,"key":null,"accuracy":15},"tackles":{"total":null,"blocks":null,"interceptions":null},"duels":{"total":1,"won":1},"dribbles":{"attempts":null,"success":null,"past":null},"fouls":{"drawn":1,"committed":null},"cards":{"yellow":0,"yellowred":0,"red":0},"penalty":{"won":null,"commited":null,"scored":0,"missed":0,"saved":0}}]},{"player":{"id":14666,"name":"I. Su\u0161ak","firstname":"Ivan","lastname":"Su\u0161ak","age":27,"birth":{"date":"1997-10-06","place":"Metkovi\u0107","country":"Croatia"},"nationality":"Croatia","height":null,"weight":null,"injured":false,"photo":"https:\/\/media.api-sports.io\/football\/players\/14666.png"},"statistics":[{"team":{"id":1018,"name":"NK Slaven Belupo","logo":"https:\/\/media.api-sports.io\/football\/teams\/1018.png"},"league":{"id":210,"name":"HNL","country":"Croatia","logo":"https:\/\/media.api-sports.io\/football\/leagues\/210.png","flag":"https:\/\/media.api-sports.io\/flags\/hr.svg","season":2023},"games":{"appearences":29,"lineups":29,"minutes":2610,"number":null,"position":"Goalkeeper","rating":"6.863157","captain":false},"substitutes":{"in":0,"out":0,"bench":3},"shots":{"total":null,"on":null},"goals":{"total":0,"conceded":34,"assists":null,"saves":62},"passes":{"total":464,"key":null,"accuracy":15},"tackles":{"total":null,"blocks":null,"interceptions":null},"duels":{"total":9,"won":9},"dribbles":{"attempts":1,"success":1,"past":null},"fouls":{"drawn":5,"committed":null},"cards":{"yellow":3,"yellowred":0,"red":0},"penalty":{"won":null,"commited":null,"scored":0,"missed":0,"saved":0}}]},{"player":{"id":14774,"name":"V. Majstorovi\u0107","firstname":"Valentino","lastname":"Majstorovi\u0107","age":29,"birth":{"date":"1995-11-11","place":null,"country":"Croatia"},"nationality":"Croatia","height":null,"weight":null,"injured":false,"photo":"https:\/\/media.api-sports.io\/football\/players\/14774.png"},"statistics":[{"team":{"id":1068,"name":"HNK Gorica","logo":"https:\/\/media.api-sports.io\/football\/teams\/1068.png"},"league":{"id":210,"name":"HNL","country":"Croatia","logo":"https:\/\/media.api-sports.io\/football\/leagues\/210.png","flag":"https:\/\/media.api-sports.io\/flags\/hr.svg","season":2023},"games":{"appearences":16,"lineups":8,"minutes":834,"number":null,"position":"Midfielder","rating":"6.675000","captain":false},"substitutes":{"in":8,"out":7,"bench":12},"shots":{"total":4,"on":3},"goals":{"total":2,"conceded":0,"assists":null,"saves":null},"passes":{"total":85,"key":4,"accuracy":8},"tackles":{"total":6,"blocks":null,"interceptions":2},"duels":{"total":64,"won":27},"dribbles":{"attempts":13,"success":4,"past":null},"fouls":{"drawn":10,"committed":12},"cards":{"yellow":1,"yellowred":1,"red":0},"penalty":{"won":null,"commited":null,"scored":0,"missed":0,"saved":null}}]},{"player":{"id":14818,"name":"M. Jesenovi\u0107","firstname":"Matija","lastname":"Jesenovi\u0107","age":27,"birth":{"date":"1997-12-19","place":"\u010cakovec","country":"Croatia"},"nationality":"Croatia","height":null,"weight":null,"injured":false,"photo":"https:\/\/media.api-sports.io\/football\/players\/14818.png"},"statistics":[{"team":{"id":1018,"name":"NK Slaven Belupo","logo":"https:\/\/media.api-sports.io\/football\/teams\/1018.png"},"league":{"id":210,"name":"HNL","country":"Croatia","logo":"https:\/\/media.api-sports.io\/football\/leagues\/210.png","flag":"https:\/\/media.api-sports.io\/flags\/hr.svg","season":2023},"games":{"appearences":0,"lineups":0,"minutes":0,"number":null,"position":"Goalkeeper","rating":null,"captain":false},"substitutes":{"in":0,"out":0,"bench":13},"shots":{"total":null,"on":null},"goals":{"total":0,"conceded":0,"assists":null,"saves":null},"passes":{"total":null,"key":null,"accuracy":null},"tackles":{"total":null,"blocks":null,"interceptions":null},"duels":{"total":null,"won":null},"dribbles":{"attempts":null,"success":null,"past":null},"fouls":{"drawn":null,"committed":null},"cards":{"yellow":0,"yellowred":0,"red":0},"penalty":{"won":null,"commited":null,"scored":0,"missed":0,"saved":0}}]},{"player":{"id":37135,"name":"T. Matav\u017e","firstname":"Tim","lastname":"Matav\u017e","age":35,"birth":{"date":"1989-01-13","place":"\u0160empeter pri Gorici","country":"Slovenia"},"nationality":"Slovenia","height":"188 cm","weight":"81 kg","injured":false,"photo":"https:\/\/media.api-sports.io\/football\/players\/37135.png"},"statistics":[{"team":{"id":1068,"name":"HNK Gorica","logo":"https:\/\/media.api-sports.io\/football\/teams\/1068.png"},"league":{"id":210,"name":"HNL","country":"Croatia","logo":"https:\/\/media.api-sports.io\/football\/leagues\/210.png","flag":"https:\/\/media.api-sports.io\/flags\/hr.svg","season":2023},"games":{"appearences":22,"lineups":13,"minutes":1130,"number":null,"position":"Attacker","rating":"6.700000","captain":false},"substitutes":{"in":9,"out":10,"bench":13},"shots":{"total":11,"on":5},"goals":{"total":5,"conceded":0,"assists":null,"saves":null},"passes":{"total":111,"key":3,"accuracy":4},"tackles":{"total":2,"blocks":null,"interceptions":null},"duels":{"total":92,"won":37},"dribbles":{"attempts":2,"success":null,"past":null},"fouls":{"drawn":11,"committed":3},"cards":{"yellow":0,"yellowred":0,"red":0},"penalty":{"won":null,"commited":null,"scored":0,"missed":0,"saved":null}}]},{"player":{"id":37467,"name":"S. Blummel","firstname":"Sven","lastname":"Blummel","age":28,"birth":{"date":"1996-09-08","place":"Schijndel","country":"Netherlands"},"nationality":"Netherlands","height":"178 cm","weight":"71 kg","injured":false,"photo":"https:\/\/media.api-sports.io\/football\/players\/37467.png"},"statistics":[{"team":{"id":1068,"name":"HNK Gorica","logo":"https:\/\/media.api-sports.io\/football\/teams\/1068.png"},"league":{"id":210,"name":"HNL","country":"Croatia","logo":"https:\/\/media.api-sports.io\/football\/leagues\/210.png","flag":"https:\/\/media.api-sports.io\/flags\/hr.svg","season":2023},"games":{"appearences":17,"lineups":3,"minutes":429,"number":null,"position":"Attacker","rating":"6.800000","captain":false},"substitutes":{"in":14,"out":4,"bench":30},"shots":{"total":7,"on":7},"goals":{"total":3,"conceded":0,"assists":null,"saves":null},"passes":{"total":83,"key":3,"accuracy":5},"tackles":{"total":3,"blocks":1,"interceptions":7},"duels":{"total":27,"won":10},"dribbles":{"attempts":3,"success":2,"past":null},"fouls":{"drawn":4,"committed":3},"cards":{"yellow":2,"yellowred":0,"red":0},"penalty":{"won":null,"commited":null,"scored":0,"missed":0,"saved":null}}]},{"player":{"id":127630,"name":"N. Vujnovi\u0107","firstname":"Nikola","lastname":"Vujnovi\u0107","age":27,"birth":{"date":"1997-01-11","place":"Cetinje","country":"Montenegro"},"nationality":"Montenegro","height":null,"weight":null,"injured":false,"photo":"https:\/\/media.api-sports.io\/football\/players\/127630.png"},"statistics":[{"team":{"id":1068,"name":"HNK Gorica","logo":"https:\/\/media.api-sports.io\/football\/teams\/1068.png"},"league":{"id":210,"name":"HNL","country":"Croatia","logo":"https:\/\/media.api-sports.io\/football\/leagues\/210.png","flag":"https:\/\/media.api-sports.io\/flags\/hr.svg","season":2023},"games":{"appearences":26,"lineups":21,"minutes":1604,"number":null,"position":"Attacker","rating":"6.788235","captain":false},"substitutes":{"in":5,"out":18,"bench":5},"shots":{"total":22,"on":13},"goals":{"total":4,"conceded":0,"assists":null,"saves":null},"passes":{"total":190,"key":7,"accuracy":7},"tackles":{"total":5,"blocks":1,"interceptions":4},"duels":{"total":119,"won":43},"dribbles":{"attempts":3,"success":1,"past":null},"fouls":{"drawn":7,"committed":22},"cards":{"yellow":1,"yellowred":0,"red":0},"penalty":{"won":null,"commited":null,"scored":0,"missed":0,"saved":null}}]},{"player":{"id":208742,"name":"Abdullah Talal Hameed","firstname":"Abdullah","lastname":"Talal Hameed","age":29,"birth":{"date":"1995-11-20","place":null,"country":"Iraq"},"nationality":"Iraq","height":null,"weight":null,"injured":false,"photo":"https:\/\/media.api-sports.io\/football\/players\/208742.png"},"statistics":[{"team":{"id":1068,"name":"HNK Gorica","logo":"https:\/\/media.api-sports.io\/football\/teams\/1068.png"},"league":{"id":210,"name":"HNL","country":"Croatia","logo":"https:\/\/media.api-sports.io\/football\/leagues\/210.png","flag":"https:\/\/media.api-sports.io\/flags\/hr.svg","season":2023},"games":{"appearences":0,"lineups":0,"minutes":0,"number":null,"position":"Midfielder","rating":null,"captain":false},"substitutes":{"in":0,"out":0,"bench":5},"shots":{"total":null,"on":null},"goals":{"total":0,"conceded":0,"assists":null,"saves":null},"passes":{"total":null,"key":null,"accuracy":null},"tackles":{"total":null,"blocks":null,"interceptions":null},"duels":{"total":null,"won":null},"dribbles":{"attempts":null,"success":null,"past":null},"fouls":{"drawn":null,"committed":null},"cards":{"yellow":0,"yellowred":0,"red":0},"penalty":{"won":null,"commited":null,"scored":0,"missed":0,"saved":null}}]},{"player":{"id":271538,"name":"L. Ile\u010di\u0107","firstname":"Lenny","lastname":"Ile\u010di\u0107","age":20,"birth":{"date":"2004-06-10","place":"Zagreb","country":"Croatia"},"nationality":"Croatia","height":"180 cm","weight":null,"injured":false,"photo":"https:\/\/media.api-sports.io\/football\/players\/271538.png"},"statistics":[{"team":{"id":1068,"name":"HNK Gorica","logo":"https:\/\/media.api-sports.io\/football\/teams\/1068.png"},"league":{"id":210,"name":"HNL","country":"Croatia","logo":"https:\/\/media.api-sports.io\/football\/leagues\/210.png","flag":"https:\/\/media.api-sports.io\/flags\/hr.svg","season":2023},"games":{"appearences":15,"lineups":2,"minutes":349,"number":null,"position":"Attacker","rating":"6.536363","captain":false},"substitutes":{"in":13,"out":2,"bench":26},"shots":{"total":3,"on":1},"goals":{"total":0,"conceded":0,"assists":1,"saves":null},"passes":{"total":55,"key":3,"accuracy":3},"tackles":{"total":7,"blocks":null,"interceptions":3},"duels":{"total":61,"won":21},"dribbles":{"attempts":12,"success":5,"past":null},"fouls":{"drawn":3,"committed":5},"cards":{"yellow":0,"yellowred":0,"red":0},"penalty":{"won":null,"commited":null,"scored":0,"missed":0,"saved":null}}]},{"player":{"id":302972,"name":"A. Lazarov","firstname":"Andrej","lastname":"Lazarov","age":25,"birth":{"date":"1999-09-08","place":null,"country":"North Macedonia"},"nationality":"North Macedonia","height":null,"weight":null,"injured":false,"photo":"https:\/\/media.api-sports.io\/football\/players\/302972.png"},"statistics":[{"team":{"id":1068,"name":"HNK Gorica","logo":"https:\/\/media.api-sports.io\/football\/teams\/1068.png"},"league":{"id":210,"name":"HNL","country":"Croatia","logo":"https:\/\/media.api-sports.io\/football\/leagues\/210.png","flag":"https:\/\/media.api-sports.io\/flags\/hr.svg","season":2023},"games":{"appearences":10,"lineups":5,"minutes":488,"number":null,"position":"Midfielder","rating":"6.337500","captain":false},"substitutes":{"in":5,"out":4,"bench":6},"shots":{"total":1,"on":1},"goals":{"total":0,"conceded":0,"assists":null,"saves":null},"passes":{"total":96,"key":2,"accuracy":8},"tackles":{"total":3,"blocks":1,"interceptions":2},"duels":{"total":40,"won":12},"dribbles":{"attempts":7,"success":1,"past":null},"fouls":{"drawn":6,"committed":9},"cards":{"yellow":4,"yellowred":0,"red":0},"penalty":{"won":null,"commited":null,"scored":0,"missed":0,"saved":null}},{"team":{"id":1019,"name":"Rudes","logo":"https:\/\/media.api-sports.io\/football\/teams\/1019.png"},"league":{"id":210,"name":"HNL","country":"Croatia","logo":"https:\/\/media.api-sports.io\/football\/leagues\/210.png","flag":"https:\/\/media.api-sports.io\/flags\/hr.svg","season":2023},"games":{"appearences":13,"lineups":8,"minutes":757,"number":null,"position":"Midfielder","rating":"6.337500","captain":false},"substitutes":{"in":5,"out":4,"bench":6},"shots":{"total":1,"on":1},"goals":{"total":1,"conceded":0,"assists":null,"saves":null},"passes":{"total":96,"key":2,"accuracy":8},"tackles":{"total":3,"blocks":1,"interceptions":2},"duels":{"total":40,"won":12},"dribbles":{"attempts":7,"success":1,"past":null},"fouls":{"drawn":6,"committed":9},"cards":{"yellow":3,"yellowred":0,"red":0},"penalty":{"won":null,"commited":null,"scored":0,"missed":0,"saved":null}}]},{"player":{"id":329285,"name":"G. Rukavina","firstname":"Gabriel","lastname":"Rukavina","age":20,"birth":{"date":"2004-01-16","place":"Zagreb","country":"Croatia"},"nationality":"Croatia","height":null,"weight":null,"injured":false,"photo":"https:\/\/media.api-sports.io\/football\/players\/329285.png"},"statistics":[{"team":{"id":1068,"name":"HNK Gorica","logo":"https:\/\/media.api-sports.io\/football\/teams\/1068.png"},"league":{"id":210,"name":"HNL","country":"Croatia","logo":"https:\/\/media.api-sports.io\/football\/leagues\/210.png","flag":"https:\/\/media.api-sports.io\/flags\/hr.svg","season":2023},"games":{"appearences":12,"lineups":11,"minutes":730,"number":null,"position":"Attacker","rating":null,"captain":false},"substitutes":{"in":1,"out":10,"bench":1},"shots":{"total":null,"on":null},"goals":{"total":1,"conceded":0,"assists":null,"saves":null},"passes":{"total":null,"key":null,"accuracy":null},"tackles":{"total":null,"blocks":null,"interceptions":null},"duels":{"total":null,"won":null},"dribbles":{"attempts":null,"success":null,"past":null},"fouls":{"drawn":null,"committed":null},"cards":{"yellow":0,"yellowred":0,"red":0},"penalty":{"won":null,"commited":null,"scored":0,"missed":0,"saved":null}},{"team":{"id":620,"name":"Dinamo Zagreb","logo":"https:\/\/media.api-sports.io\/football\/teams\/620.png"},"league":{"id":210,"name":"HNL","country":"Croatia","logo":"https:\/\/media.api-sports.io\/football\/leagues\/210.png","flag":"https:\/\/media.api-sports.io\/flags\/hr.svg","season":2023},"games":{"appearences":2,"lineups":0,"minutes":32,"number":null,"position":"Attacker","rating":null,"captain":false},"substitutes":{"in":2,"out":0,"bench":14},"shots":{"total":null,"on":null},"goals":{"total":0,"conceded":0,"assists":null,"saves":null},"passes":{"total":null,"key":null,"accuracy":null},"tackles":{"total":null,"blocks":null,"interceptions":null},"duels":{"total":null,"won":null},"dribbles":{"attempts":null,"success":null,"past":null},"fouls":{"drawn":null,"committed":null},"cards":{"yellow":0,"yellowred":0,"red":0},"penalty":{"won":null,"commited":null,"scored":0,"missed":0,"saved":null}}]},{"player":{"id":337630,"name":"A. Juri\u010d","firstname":"Ante Matej","lastname":"Juri\u010d","age":22,"birth":{"date":"2002-11-26","place":null,"country":"Croatia"},"nationality":"Croatia","height":null,"weight":null,"injured":false,"photo":"https:\/\/media.api-sports.io\/football\/players\/337630.png"},"statistics":[{"team":{"id":1068,"name":"HNK Gorica","logo":"https:\/\/media.api-sports.io\/football\/teams\/1068.png"},"league":{"id":210,"name":"HNL","country":"Croatia","logo":"https:\/\/media.api-sports.io\/football\/leagues\/210.png","flag":"https:\/\/media.api-sports.io\/flags\/hr.svg","season":2023},"games":{"appearences":28,"lineups":7,"minutes":972,"number":null,"position":"Attacker","rating":"6.594444","captain":false},"substitutes":{"in":21,"out":6,"bench":24},"shots":{"total":10,"on":4},"goals":{"total":3,"conceded":0,"assists":2,"saves":null},"passes":{"total":179,"key":4,"accuracy":5},"tackles":{"total":12,"blocks":3,"interceptions":5},"duels":{"total":119,"won":53},"dribbles":{"attempts":11,"success":5,"past":null},"fouls":{"drawn":5,"committed":15},"cards":{"yellow":8,"yellowred":0,"red":0},"penalty":{"won":null,"commited":null,"scored":0,"missed":1,"saved":null}}]},{"player":{"id":342221,"name":"L. Nezirovi\u0107","firstname":"Lovro","lastname":"Nezirovi\u0107","age":19,"birth":{"date":"2005-05-27","place":null,"country":"Croatia"},"nationality":"Croatia","height":null,"weight":null,"injured":false,"photo":"https:\/\/media.api-sports.io\/football\/players\/342221.png"},"statistics":[{"team":{"id":1068,"name":"HNK Gorica","logo":"https:\/\/media.api-sports.io\/football\/teams\/1068.png"},"league":{"id":210,"name":"HNL","country":"Croatia","logo":"https:\/\/media.api-sports.io\/football\/leagues\/210.png","flag":"https:\/\/media.api-sports.io\/flags\/hr.svg","season":2023},"games":{"appearences":0,"lineups":0,"minutes":0,"number":null,"position":"Attacker","rating":null,"captain":false},"substitutes":{"in":0,"out":0,"bench":0},"shots":{"total":null,"on":null},"goals":{"total":0,"conceded":null,"assists":null,"saves":null},"passes":{"total":null,"key":null,"accuracy":null},"tackles":{"total":null,"blocks":null,"interceptions":null},"duels":{"total":null,"won":null},"dribbles":{"attempts":null,"success":null,"past":null},"fouls":{"drawn":null,"committed":null},"cards":{"yellow":0,"yellowred":0,"red":0},"penalty":{"won":null,"commited":null,"scored":null,"missed":null,"saved":null}}]},{"player":{"id":375307,"name":"L. Kapulica","firstname":"Luka","lastname":"Kapulica","age":19,"birth":{"date":"2005-01-18","place":null,"country":"Croatia"},"nationality":"Croatia","height":null,"weight":null,"injured":false,"photo":"https:\/\/media.api-sports.io\/football\/players\/375307.png"},"statistics":[{"team":{"id":1068,"name":"HNK Gorica","logo":"https:\/\/media.api-sports.io\/football\/teams\/1068.png"},"league":{"id":210,"name":"HNL","country":"Croatia","logo":"https:\/\/media.api-sports.io\/football\/leagues\/210.png","flag":"https:\/\/media.api-sports.io\/flags\/hr.svg","season":2023},"games":{"appearences":24,"lineups":4,"minutes":555,"number":null,"position":"Midfielder","rating":"6.652941","captain":false},"substitutes":{"in":20,"out":4,"bench":27},"shots":{"total":3,"on":1},"goals":{"total":0,"conceded":0,"assists":1,"saves":null},"passes":{"total":205,"key":6,"accuracy":8},"tackles":{"total":14,"blocks":5,"interceptions":5},"duels":{"total":79,"won":32},"dribbles":{"attempts":17,"success":10,"past":null},"fouls":{"drawn":4,"committed":10},"cards":{"yellow":1,"yellowred":0,"red":0},"penalty":{"won":null,"commited":null,"scored":0,"missed":0,"saved":null}}]},{"player":{"id":450964,"name":"S. Sagna","firstname":"Sekou Matar","lastname":"Sagna","age":20,"birth":{"date":"2004-01-06","place":"Koubalan","country":"Senegal"},"nationality":"Senegal","height":"171 cm","weight":null,"injured":false,"photo":"https:\/\/media.api-sports.io\/football\/players\/450964.png"},"statistics":[{"team":{"id":1068,"name":"HNK Gorica","logo":"https:\/\/media.api-sports.io\/football\/teams\/1068.png"},"league":{"id":210,"name":"HNL","country":"Croatia","logo":"https:\/\/media.api-sports.io\/football\/leagues\/210.png","flag":"https:\/\/media.api-sports.io\/flags\/hr.svg","season":2023},"games":{"appearences":7,"lineups":0,"minutes":72,"number":null,"position":"Midfielder","rating":"6.440000","captain":false},"substitutes":{"in":7,"out":0,"bench":18},"shots":{"total":null,"on":null},"goals":{"total":0,"conceded":0,"assists":null,"saves":null},"passes":{"total":39,"key":null,"accuracy":5},"tackles":{"total":1,"blocks":null,"interceptions":2},"duels":{"total":14,"won":7},"dribbles":{"attempts":null,"success":null,"past":null},"fouls":{"drawn":5,"committed":2},"cards":{"yellow":0,"yellowred":0,"red":0},"penalty":{"won":null,"commited":null,"scored":0,"missed":0,"saved":null}}]},{"player":{"id":452386,"name":"A. Fall","firstname":"Arona","lastname":"Fall","age":19,"birth":{"date":"2005-01-05","place":"Boune","country":"Senegal"},"nationality":"Senegal","height":"175 cm","weight":null,"injured":false,"photo":"https:\/\/media.api-sports.io\/football\/players\/452386.png"},"statistics":[{"team":{"id":1068,"name":"HNK Gorica","logo":"https:\/\/media.api-sports.io\/football\/teams\/1068.png"},"league":{"id":210,"name":"HNL","country":"Croatia","logo":"https:\/\/media.api-sports.io\/football\/leagues\/210.png","flag":"https:\/\/media.api-sports.io\/flags\/hr.svg","season":2023},"games":{"appearences":3,"lineups":0,"minutes":27,"number":null,"position":"Attacker","rating":"6.700000","captain":false},"substitutes":{"in":3,"out":0,"bench":7},"shots":{"total":null,"on":null},"goals":{"total":0,"conceded":0,"assists":null,"saves":null},"passes":{"total":8,"key":null,"accuracy":3},"tackles":{"total":3,"blocks":null,"interceptions":null},"duels":{"total":12,"won":6},"dribbles":{"attempts":3,"success":1,"past":null},"fouls":{"drawn":2,"committed":1},"cards":{"yellow":0,"yellowred":0,"red":0},"penalty":{"won":null,"commited":null,"scored":0,"missed":0,"saved":null}}]},{"player":{"id":455123,"name":"F. \u0160a\u0161ek","firstname":"Fabijan","lastname":"\u0160a\u0161ek","age":19,"birth":{"date":"2005-09-17","place":"Koprivnica","country":"Croatia"},"nationality":"Croatia","height":null,"weight":null,"injured":false,"photo":"https:\/\/media.api-sports.io\/football\/players\/455123.png"},"statistics":[{"team":{"id":1018,"name":"NK Slaven Belupo","logo":"https:\/\/media.api-sports.io\/football\/teams\/1018.png"},"league":{"id":210,"name":"HNL","country":"Croatia","logo":"https:\/\/media.api-sports.io\/football\/leagues\/210.png","flag":"https:\/\/media.api-sports.io\/flags\/hr.svg","season":2023},"games":{"appearences":0,"lineups":0,"minutes":0,"number":null,"position":"Goalkeeper","rating":null,"captain":false},"substitutes":{"in":0,"out":0,"bench":7},"shots":{"total":null,"on":null},"goals":{"total":0,"conceded":0,"assists":null,"saves":null},"passes":{"total":null,"key":null,"accuracy":null},"tackles":{"total":null,"blocks":null,"interceptions":null},"duels":{"total":null,"won":null},"dribbles":{"attempts":null,"success":null,"past":null},"fouls":{"drawn":null,"committed":null},"cards":{"yellow":0,"yellowred":0,"red":0},"penalty":{"won":null,"commited":null,"scored":0,"missed":0,"saved":0}}]},{"player":{"id":459720,"name":"T. Kolar","firstname":"Teo","lastname":"Kolar","age":17,"birth":{"date":"2007-01-24","place":null,"country":"Croatia"},"nationality":"Croatia","height":null,"weight":null,"injured":false,"photo":"https:\/\/media.api-sports.io\/football\/players\/459720.png"},"statistics":[{"team":{"id":1018,"name":"NK Slaven Belupo","logo":"https:\/\/media.api-sports.io\/football\/teams\/1018.png"},"league":{"id":210,"name":"HNL","country":"Croatia","logo":"https:\/\/media.api-sports.io\/football\/leagues\/210.png","flag":"https:\/\/media.api-sports.io\/flags\/hr.svg","season":2023},"games":{"appearences":0,"lineups":0,"minutes":0,"number":null,"position":"Goalkeeper","rating":null,"captain":false},"substitutes":{"in":0,"out":0,"bench":2},"shots":{"total":null,"on":null},"goals":{"total":0,"conceded":0,"assists":null,"saves":null},"passes":{"total":null,"key":null,"accuracy":null},"tackles":{"total":null,"blocks":null,"interceptions":null},"duels":{"total":null,"won":null},"dribbles":{"attempts":null,"success":null,"past":null},"fouls":{"drawn":null,"committed":null},"cards":{"yellow":0,"yellowred":0,"red":0},"penalty":{"won":null,"commited":null,"scored":0,"missed":0,"saved":0}}]},{"player":{"id":462234,"name":"L. Vrzi\u0107","firstname":"Luka","lastname":"Vrzi\u0107","age":17,"birth":{"date":"2007-01-05","place":"Zagreb","country":"Croatia"},"nationality":"Croatia","height":null,"weight":null,"injured":false,"photo":"https:\/\/media.api-sports.io\/football\/players\/462234.png"},"statistics":[{"team":{"id":1068,"name":"HNK Gorica","logo":"https:\/\/media.api-sports.io\/football\/teams\/1068.png"},"league":{"id":210,"name":"HNL","country":"Croatia","logo":"https:\/\/media.api-sports.io\/football\/leagues\/210.png","flag":"https:\/\/media.api-sports.io\/flags\/hr.svg","season":2023},"games":{"appearences":4,"lineups":0,"minutes":33,"number":null,"position":"Midfielder","rating":"6.300000","captain":false},"substitutes":{"in":4,"out":0,"bench":4},"shots":{"total":null,"on":null},"goals":{"total":0,"conceded":0,"assists":null,"saves":null},"passes":{"total":10,"key":null,"accuracy":2},"tackles":{"total":1,"blocks":null,"interceptions":null},"duels":{"total":5,"won":2},"dribbles":{"attempts":2,"success":null,"past":null},"fouls":{"drawn":1,"committed":null},"cards":{"yellow":0,"yellowred":0,"red":0},"penalty":{"won":null,"commited":null,"scored":0,"missed":0,"saved":null}}]}]}